setup.cfg
setup.py
rum_generic.egg-info/PKG-INFO
rum_generic.egg-info/SOURCES.txt
rum_generic.egg-info/dependency_links.txt
rum_generic.egg-info/entry_points.txt
rum_generic.egg-info/not-zip-safe
rum_generic.egg-info/requires.txt
rum_generic.egg-info/top_level.txt
rumgeneric/__init__.py