Metadata-Version: 1.0
Name: rum-generic
Version: 0.3.0dev
Summary: Generic Functions  Builder from RUM
Home-page: http://bitbucket.org/brickenstein/rum-generic
Author: Alberto Vaverde Gonzalez, Michael Brickenstein
Author-email: rum-discuss@googlegroups.com
License: MIT
Keywords: peak.rules
Platform: UNKNOWN
